pyserxng/__init__.py
pyserxng/client.py
pyserxng/config.py
pyserxng/exceptions.py
pyserxng/instance_manager.py
pyserxng/local_client.py
pyserxng/models.py
pyserxng/search_parser.py
pyserxng/utils.py
pyserxng-0.1.0.dist-info/licenses/LICENSE
pyserxng-0.1.0.dist-info/METADATA
pyserxng-0.1.0.dist-info/WHEEL
pyserxng-0.1.0.dist-info/top_level.txt
pyserxng-0.1.0.dist-info/RECORD
